usenc/__init__.py
usenc/cli.py
usenc/core.py
usenc/utils.py
usenc/encoders/__init__.py
usenc/encoders/base16.py
usenc/encoders/base2n.py
usenc/encoders/base32.py
usenc/encoders/base64.py
usenc/encoders/cstring.py
usenc/encoders/doubleurl.py
usenc/encoders/encoder.py
usenc/encoders/escape.py
usenc/encoders/hash.py
usenc/encoders/hex.py
usenc/encoders/html.py
usenc/encoders/md5.py
usenc/encoders/sha1.py
usenc/encoders/sha256.py
usenc/encoders/unicode.py
usenc/encoders/url.py
usenc-1.0.0.dist-info/METADATA
usenc-1.0.0.dist-info/WHEEL
usenc-1.0.0.dist-info/entry_points.txt
usenc-1.0.0.dist-info/licenses/LICENSE
usenc-1.0.0.dist-info/RECORD
