Metadata-Version: 2.4
Name: usenc
Version: 1.0.0
Summary: A Universal String Encoder
Project-URL: Homepage, https://crashoz.github.io/usenc/
Project-URL: Documentation, https://crashoz.github.io/usenc/
Project-URL: Repository, https://github.com/crashoz/usenc
Project-URL: Bug Tracker, https://github.com/crashoz/usenc/issues
Project-URL: Changelog, https://github.com/crashoz/usenc/blob/main/CHANGELOG.md
Author-email: Xavier 'crashoz' Launey <xavier.launey@gmail.com>
Maintainer-email: Xavier 'crashoz' Launey <xavier.launey@gmail.com>
License: MIT
License-File: LICENSE
Keywords: decoder,encoder,encodings,string
Classifier: Development Status :: 3 - Alpha
Classifier: Environment :: Console
Classifier: Intended Audience :: Developers
Classifier: Intended Audience :: System Administrators
Classifier: License :: OSI Approved :: MIT License
Classifier: Natural Language :: English
Classifier: Operating System :: OS Independent
Classifier: Programming Language :: Python :: 3
Classifier: Programming Language :: Python :: 3 :: Only
Classifier: Programming Language :: Python :: 3.8
Classifier: Programming Language :: Python :: 3.9
Classifier: Programming Language :: Python :: 3.10
Classifier: Programming Language :: Python :: 3.11
Classifier: Programming Language :: Python :: 3.12
Classifier: Topic :: Internet
Classifier: Topic :: Security :: Cryptography
Classifier: Topic :: Software Development :: Libraries :: Python Modules
Classifier: Topic :: Text Processing
Classifier: Topic :: Utilities
Classifier: Typing :: Typed
Requires-Python: >=3.8
Provides-Extra: dev
Requires-Dist: bandit[toml]>=1.7.0; extra == 'dev'
Requires-Dist: mypy>=1.11.0; extra == 'dev'
Requires-Dist: pre-commit>=3.5.0; extra == 'dev'
Requires-Dist: pytest-cov; extra == 'dev'
Requires-Dist: pytest>=7.0; extra == 'dev'
Requires-Dist: ruff>=0.8.0; extra == 'dev'
Provides-Extra: docs
Requires-Dist: mkdocs-awesome-nav>=3.0.0; extra == 'docs'
Requires-Dist: mkdocs-material>=9.0.0; extra == 'docs'
Requires-Dist: mkdocs>=1.5.0; extra == 'docs'
Requires-Dist: mkdocstrings[python]>=0.24.0; extra == 'docs'
